LICENSE
MANIFEST.in
README
setup.py
libtele.egg-info/PKG-INFO
libtele.egg-info/SOURCES.txt
libtele.egg-info/dependency_links.txt
libtele.egg-info/top_level.txt
tele/__init__.py
tele/channel.py
tele/client.py
tele/show.py