Metadata-Version: 1.1
Name: libtele
Version: 0.3
Summary: Library for interfacing http://tele.at/.
Home-page: https://github.com/kaini/libtele
Author: Michael Kainer
Author-email: kaini1123@gmail.com
License: GPLv3
Platform: UNKNOWN
Classifier: Development Status :: 4 - Beta
Classifier: Framework :: Twisted
Classifier: Intended Audience :: Developers
Classifier: License :: OSI Approved :: GNU General Public License (GPL)
Classifier: Natural Language :: English
Classifier: Natural Language :: German
Classifier: Operating System :: OS Independent
Classifier: Programming Language :: Python :: 2.6
Classifier: Programming Language :: Python :: 2.7
Classifier: Topic :: Software Development :: Libraries :: Python Modules
Classifier: Topic :: Utilities
Classifier: Topic :: Internet
Requires: lxml
Requires: pytz
Requires: twisted
Provides: tele
